odoo/addons/shopinvader_api_cart_step/README.rst
odoo/addons/shopinvader_api_cart_step/__init__.py
odoo/addons/shopinvader_api_cart_step/__manifest__.py
odoo/addons/shopinvader_api_cart_step/helper.py
odoo/addons/shopinvader_api_cart_step/i18n/shopinvader_api_cart_step.pot
odoo/addons/shopinvader_api_cart_step/readme/CONTRIBUTORS.rst
odoo/addons/shopinvader_api_cart_step/readme/DESCRIPTION.rst
odoo/addons/shopinvader_api_cart_step/schemas/__init__.py
odoo/addons/shopinvader_api_cart_step/schemas/cart.py
odoo/addons/shopinvader_api_cart_step/schemas/sale.py
odoo/addons/shopinvader_api_cart_step/static/description/index.html
odoo/addons/shopinvader_api_cart_step/tests/__init__.py
odoo/addons/shopinvader_api_cart_step/tests/test_api_cart_step.py
odoo_addon_shopinvader_api_cart_step-16.0.1.0.1.dist-info/METADATA
odoo_addon_shopinvader_api_cart_step-16.0.1.0.1.dist-info/WHEEL
odoo_addon_shopinvader_api_cart_step-16.0.1.0.1.dist-info/top_level.txt
odoo_addon_shopinvader_api_cart_step-16.0.1.0.1.dist-info/RECORD
